ironvaultmd/__init__.py
ironvaultmd/ironvault.py
ironvaultmd/util.py
ironvaultmd/parsers/__init__.py
ironvaultmd/parsers/base.py
ironvaultmd/parsers/blocks.py
ironvaultmd/parsers/context.py
ironvaultmd/parsers/nodes.py
ironvaultmd/parsers/templater.py
ironvaultmd/parsers/templates/link.html
ironvaultmd/parsers/templates/blocks/actor.html
ironvaultmd/parsers/templates/blocks/block.html
ironvaultmd/parsers/templates/blocks/mechanics.html
ironvaultmd/parsers/templates/blocks/move.html
ironvaultmd/parsers/templates/blocks/oracle.html
ironvaultmd/parsers/templates/blocks/test.html
ironvaultmd/parsers/templates/nodes/add.html
ironvaultmd/parsers/templates/nodes/burn.html
ironvaultmd/parsers/templates/nodes/clock.html
ironvaultmd/parsers/templates/nodes/impact.html
ironvaultmd/parsers/templates/nodes/initiative.html
ironvaultmd/parsers/templates/nodes/meter.html
ironvaultmd/parsers/templates/nodes/move.html
ironvaultmd/parsers/templates/nodes/node.html
ironvaultmd/parsers/templates/nodes/ooc.html
ironvaultmd/parsers/templates/nodes/oracle.html
ironvaultmd/parsers/templates/nodes/position.html
ironvaultmd/parsers/templates/nodes/progress.html
ironvaultmd/parsers/templates/nodes/progress_roll.html
ironvaultmd/parsers/templates/nodes/reroll.html
ironvaultmd/parsers/templates/nodes/roll.html
ironvaultmd/parsers/templates/nodes/roll_result.html
ironvaultmd/parsers/templates/nodes/test.html
ironvaultmd/parsers/templates/nodes/track.html
ironvaultmd/parsers/templates/nodes/xp.html
ironvaultmd/processors/__init__.py
ironvaultmd/processors/frontmatter.py
ironvaultmd/processors/links.py
ironvaultmd/processors/mechanics.py
ironvaultmd-0.5.2.dist-info/METADATA
ironvaultmd-0.5.2.dist-info/WHEEL
ironvaultmd-0.5.2.dist-info/licenses/LICENSE
ironvaultmd-0.5.2.dist-info/RECORD
