Metadata-Version: 2.4
Name: ironvaultmd
Version: 0.5.2
Summary: Python-Markdown extension for parsing Iron Vault journals
Project-URL: Homepage, https://github.com/sgreg/iron-vault-mdparser
Project-URL: Issues, https://github.com/sgreg/iron-vault-mdparser/issues
Author-email: Sven Gregori <sven@craplab.fi>
License-Expression: MIT
License-File: LICENSE
Classifier: Development Status :: 3 - Alpha
Classifier: Environment :: Console
Classifier: Intended Audience :: Developers
Classifier: License :: OSI Approved :: MIT License
Classifier: Operating System :: OS Independent
Classifier: Programming Language :: Python :: 3
Classifier: Topic :: Games/Entertainment :: Role-Playing
Classifier: Topic :: Software Development :: Libraries :: Python Modules
Classifier: Topic :: Text Processing :: Markup :: HTML
Classifier: Topic :: Text Processing :: Markup :: Markdown
Requires-Python: >=3.10
Requires-Dist: jinja2
Requires-Dist: markdown
Requires-Dist: pyyaml
